{
  "description": "Servidor XMPP multiplataforma escrito en Java.",
  "license_url": "https://projects.tigase.org/projects/tigase-server/repository/revisions/master/changes/COPYING",
  "logo": "tigase.png",
  "notes": "",
  "privacy_url": "",
  "source_url": "https://projects.tigase.org/projects/tigase-server/repository",
  "name": "Tigase",
  "tos_url": "",
  "url": "http://www.tigase.org/",
  "wikipedia_url": "https://en.wikipedia.org/wiki/Tigase",
  "protocols": [
    "XMPP"
  ],
  "categories": [
    {
      "name": "Servers",
      "subcategories": [
        {
          "name": "XMPP Servers",
          "slug": "xmpp-servers"
        }
      ],
      "slug": "servers"
    }
  ],
  "slug": "tigase",
  "protocolsSlugged": [
    {
      "name": "XMPP",
      "slug": "xmpp"
    }
  ]
}